llm/__init__.py
llm/anthropic.py
llm/chat_completions.py
llm/client.py
llm/responses_api.py
llm/streaming.py
llm/streaming_responses.py
llm/tool_handling.py
llm/tooling.py
llm/types.py
unified_llm_client-0.2.1.dist-info/licenses/LICENSE
unified_llm_client-0.2.1.dist-info/METADATA
unified_llm_client-0.2.1.dist-info/WHEEL
unified_llm_client-0.2.1.dist-info/top_level.txt
unified_llm_client-0.2.1.dist-info/RECORD
