Metadata-Version: 2.4
Name: unified-llm-client
Version: 0.2.1
Summary: A unified async client for interacting with multiple LLM providers
Home-page: https://github.com/skitsanos/unified-llm-client
Author: skitsanos
Author-email: skitsanos <info@skitsanos.com>
License-Expression: MIT
Project-URL: Homepage, https://github.com/skitsanos/unified-llm-client
Project-URL: Bug Tracker, https://github.com/skitsanos/unified-llm-client/issues
Keywords: llm,openai,anthropic,gpt,claude,ai,machine learning,ollama
Classifier: Programming Language :: Python :: 3
Classifier: Programming Language :: Python :: 3.8
Classifier: Programming Language :: Python :: 3.9
Classifier: Programming Language :: Python :: 3.10
Classifier: Programming Language :: Python :: 3.11
Classifier: Operating System :: OS Independent
Classifier: Development Status :: 4 - Beta
Classifier: Intended Audience :: Developers
Classifier: Topic :: Software Development :: Libraries :: Python Modules
Requires-Python: >=3.8
License-File: LICENSE
Requires-Dist: anthropic>=0.22.0
Requires-Dist: openai>=1.28.0
Requires-Dist: python-dotenv>=1.0.0
Dynamic: author
Dynamic: home-page
Dynamic: license-file
Dynamic: requires-python
